amypet/__init__.py
amypet/__main__.py
amypet/_backend_web.py
amypet/_dist_ver.py
amypet/aux.py
amypet/backend_centiloid.py
amypet/centiloid.py
amypet/cli.py
amypet/config_icon.png
amypet/dcm2nii.py
amypet/gui.py
amypet/imscroll.py
amypet/imtrimup.py
amypet/preproc.py
amypet/program_icon.png
amypet/suvr_tools.py
amypet/utils.py
amypet/web.py
amypet/centiloid_old/__init__.py
amypet/centiloid_old/f_1CorregisterEstimate.m
amypet/centiloid_old/f_2CorregisterEstimate.m
amypet/centiloid_old/f_3Segment.m
amypet/centiloid_old/f_4Normalise.m
amypet/centiloid_old/f_Quant_centiloid.m
amypet/centiloid_old/f_acpcReorientation.m
amypet/centiloid_old/f_noNaN.m
amypet/data/CL_masks/voi_CerebGry_1mm.nii
amypet/data/CL_masks/voi_CerebGry_2mm.nii
amypet/data/CL_masks/voi_Pons_1mm.nii
amypet/data/CL_masks/voi_Pons_2mm.nii
amypet/data/CL_masks/voi_WhlCblBrnStm_1mm.nii
amypet/data/CL_masks/voi_WhlCblBrnStm_2mm.nii
amypet/data/CL_masks/voi_WhlCbl_1mm.nii
amypet/data/CL_masks/voi_WhlCbl_2mm.nii
amypet/data/CL_masks/voi_ctx_1mm.nii
amypet/data/CL_masks/voi_ctx_2mm.nii
amypet/data/cl_anchor_tables/CL_PiB_anchors.pkl
amypet/data/cl_anchor_tables/suvr_fbb_to_suvr_pib__transform.pkl
amypet/data/cl_anchor_tables/suvr_fbp_to_suvr_pib__transform.pkl
amypet/data/cl_anchor_tables/suvr_flute_to_suvr_pib__transform.pkl
amypet-1.6.0.dist-info/LICENCE.md
amypet-1.6.0.dist-info/METADATA
amypet-1.6.0.dist-info/WHEEL
amypet-1.6.0.dist-info/entry_points.txt
amypet-1.6.0.dist-info/top_level.txt
amypet-1.6.0.dist-info/RECORD
