Metadata-Version: 2.1
Name: amypet
Version: 1.6.0
Summary: Amyloid imaging to prevent Alzheimer's Disease
Home-page: https://amypad.eu
Maintainer: Casper da Costa-Luis
Maintainer-email: casper.dcl@physics.org
License: MPL 2.0
Project-URL: Repository, https://github.com/AMYPAD/AmyPET
Project-URL: Changelog, https://github.com/AMYPAD/AmyPET/releases
Project-URL: Documentation, https://github.com/AMYPAD/AmyPET/#AmyPET
Keywords: pet,alzheimers
Platform: any
Classifier: Development Status :: 3 - Alpha
Classifier: Intended Audience :: Developers
Classifier: Intended Audience :: Education
Classifier: Intended Audience :: Healthcare Industry
Classifier: Intended Audience :: Science/Research
Classifier: License :: OSI Approved :: Mozilla Public License 2.0 (MPL 2.0)
Classifier: Operating System :: Microsoft :: Windows
Classifier: Operating System :: POSIX :: Linux
Classifier: Programming Language :: Python :: 3
Classifier: Programming Language :: Python :: 3.6
Classifier: Programming Language :: Python :: 3.7
Classifier: Programming Language :: Python :: 3.8
Classifier: Programming Language :: Python :: 3.9
Classifier: Programming Language :: Python :: 3.10
Classifier: Programming Language :: Python :: 3 :: Only
Classifier: Topic :: Scientific/Engineering :: Medical Science Apps.
Classifier: Topic :: Software Development :: Libraries
Classifier: Topic :: Software Development :: Libraries :: Python Modules
Classifier: Topic :: Software Development :: User Interfaces
Classifier: Topic :: System :: Installation/Setup
Classifier: Topic :: Utilities
Provides: amypet
Requires-Python: >=3.6
License-File: LICENCE.md
Requires-Dist: argopt
Requires-Dist: miutil[cuda,nii] (>=0.9.0)
Requires-Dist: niftypad (>=1.1.1)
Requires-Dist: nimpa
Requires-Dist: setuptools
Requires-Dist: shtab (>1.3.2)
Requires-Dist: spm12
Requires-Dist: streamlit (>=0.85.2)
Requires-Dist: tqdm
Provides-Extra: dev
Requires-Dist: pytest ; extra == 'dev'
Requires-Dist: pytest-cov ; extra == 'dev'
Requires-Dist: pytest-timeout ; extra == 'dev'
Requires-Dist: pytest-xdist ; extra == 'dev'
Provides-Extra: gui
Requires-Dist: Gooey (>=1.0.8) ; extra == 'gui'
Provides-Extra: niftypet
Requires-Dist: niftypet (>=0.0.1) ; extra == 'niftypet'
Provides-Extra: web
